LICENSE
MANIFEST.in
Makefile
README.rst
VERSION
bower.json
setup.py
grano/__init__.py
grano/ui/__init__.py
grano/ui/base.py
grano/ui/view.py
grano/ui/static/layout.html
grano/ui/static/images/c4a.png
grano/ui/static/images/home.png
grano/ui/static/images/logo.png
grano/ui/static/images/refine.png
grano/ui/static/js/app.js
grano/ui/static/js/config.js
grano/ui/static/js/util.js
grano/ui/static/js/validation.js
grano/ui/static/js/controllers/accounts.js
grano/ui/static/js/controllers/app.js
grano/ui/static/js/controllers/entities.js
grano/ui/static/js/controllers/home.js
grano/ui/static/js/controllers/imports.js
grano/ui/static/js/controllers/permissions.js
grano/ui/static/js/controllers/projects.js
grano/ui/static/js/controllers/query.js
grano/ui/static/js/controllers/relations.js
grano/ui/static/js/controllers/schemata.js
grano/ui/static/js/directives/entity_frame.js
grano/ui/static/js/directives/entity_suggest.js
grano/ui/static/js/directives/pager.js
grano/ui/static/js/directives/permission.js
grano/ui/static/js/directives/property_edit.js
grano/ui/static/js/directives/property_list.js
grano/ui/static/js/directives/property_view.js
grano/ui/static/js/directives/query_graph.js
grano/ui/static/js/directives/query_panel.js
grano/ui/static/js/directives/query_panel_layer.js
grano/ui/static/js/directives/query_table.js
grano/ui/static/js/directives/relation_frame.js
grano/ui/static/js/directives/relation_list.js
grano/ui/static/js/directives/settings_frame.js
grano/ui/static/js/filters/datetime.js
grano/ui/static/js/filters/truncate.js
grano/ui/static/js/services/core.js
grano/ui/static/js/services/metadata.js
grano/ui/static/js/services/query_utils.js
grano/ui/static/js/services/session.js
grano/ui/static/style/main.less
grano/ui/static/style/variables.less
grano/ui/static/templates/account.html
grano/ui/static/templates/home.html
grano/ui/static/templates/query.html
grano/ui/static/templates/directives/entity_frame.html
grano_ui.egg-info/PKG-INFO
grano_ui.egg-info/SOURCES.txt
grano_ui.egg-info/dependency_links.txt
grano_ui.egg-info/entry_points.txt
grano_ui.egg-info/namespace_packages.txt
grano_ui.egg-info/not-zip-safe
grano_ui.egg-info/requires.txt
grano_ui.egg-info/top_level.txt