Metadata-Version: 1.1
Name: grano-ui
Version: 0.4.7
Summary: An entity and social network tracking software for news applications (Admin UI)
Home-page: http://granoproject.org
Author: Code for Africa / ANCIR
Author-email: support@codeforafrica.org
License: MIT
Keywords: sql graph sna networks journalism ddj entities
Platform: UNKNOWN
Classifier: Development Status :: 3 - Alpha
Classifier: Intended Audience :: Developers
Classifier: Operating System :: OS Independent
Classifier: Programming Language :: Python
